nonebot_plugin_wol/__init__.py
nonebot_plugin_wol/config.py
nonebot_plugin_wol/img/help.png
nonebot_plugin_wol/tools/wol.py
nonebot_plugin_wol-1.0.4.dist-info/LICENSE
nonebot_plugin_wol-1.0.4.dist-info/METADATA
nonebot_plugin_wol-1.0.4.dist-info/WHEEL
nonebot_plugin_wol-1.0.4.dist-info/top_level.txt
nonebot_plugin_wol-1.0.4.dist-info/RECORD
