Metadata-Version: 2.1
Name: nonebot-plugin-wol
Version: 1.0.4
Summary: A WOL Nonebot plugin
Home-page: https://github.com/twoonefour/nonebot_plugin_wol.git
Author: TwoOnefour
Author-email: TwoOnefour <lys214412@gmail.com>
License: LICENSE
Project-URL: Homepage, https://github.com/twoonefour/nonebot_plugin_wol
Classifier: Programming Language :: Python :: 3
Classifier: License :: OSI Approved :: MIT License
Classifier: Operating System :: OS Independent
Requires-Python: >=3.6
License-File: LICENSE
Requires-Dist: ping3 (>=4.0.4)
Requires-Dist: nonebot2 (>=2.0.0rc2)
Requires-Dist: nb-cli (>=0.6.8)
Requires-Dist: nonebot-plugin-apscheduler (>=0.2.0)
